xacto/__init__.py
xacto-0.8.7.dist-info/DESCRIPTION.rst
xacto-0.8.7.dist-info/METADATA
xacto-0.8.7.dist-info/RECORD
xacto-0.8.7.dist-info/WHEEL
xacto-0.8.7.dist-info/entry_points.txt
xacto-0.8.7.dist-info/metadata.json
xacto-0.8.7.dist-info/top_level.txt
