Metadata-Version: 1.1
Name: xacto
Version: 0.8.7
Summary: Generate command-line interfaces (CLI) by introspecting callables
Home-page: http://github.com/xtfxme/xacto
Author: C Anthony Risinger
Author-email: c@anthonyrisinger.com
License: BSD
Download-URL: https://github.com/xtfxme/xacto/archive/0.8.7.zip
Keywords: cli commandline command introspection generate
Platform: UNKNOWN
Classifier: Development Status :: 4 - Beta
Classifier: Environment :: Console
Classifier: Intended Audience :: Developers
Classifier: Topic :: Software Development :: Libraries
Classifier: Topic :: Software Development :: Libraries :: Python Modules
Classifier: License :: OSI Approved :: BSD License
Classifier: Operating System :: OS Independent
Classifier: Operating System :: POSIX
Classifier: Operating System :: MacOS :: MacOS X
Classifier: Operating System :: Microsoft :: Windows
Classifier: Programming Language :: Python
Classifier: Programming Language :: Python :: 2
Classifier: Programming Language :: Python :: 3
Classifier: Programming Language :: Python :: 2.7
Classifier: Programming Language :: Python :: 3.2
Classifier: Programming Language :: Python :: 3.3
Classifier: Programming Language :: Python :: 3.4
